tinycal/__init__.py
tinycal/__main__.py
tinycal/cli.py
tinycal/config.py
tinycal/declarative_config.py
tinycal/render.py
tinycal/tcal.py
tinycal-0.3.3.dist-info/LICENSE.txt
tinycal-0.3.3.dist-info/METADATA
tinycal-0.3.3.dist-info/WHEEL
tinycal-0.3.3.dist-info/entry_points.txt
tinycal-0.3.3.dist-info/top_level.txt
tinycal-0.3.3.dist-info/RECORD
