Metadata-Version: 2.1
Name: tinycal
Version: 0.3.3
Summary: A Python implementation of cal utility
Home-page: UNKNOWN
Author: Chang-Yen Chih
Author-email: michael66230@gmail.com
License: UNKNOWN
Platform: UNKNOWN
Classifier: Development Status :: 3 - Alpha
Classifier: Environment :: Console
Classifier: Intended Audience :: End Users/Desktop
Classifier: License :: OSI Approved :: BSD License
Classifier: Natural Language :: English
Classifier: Operating System :: POSIX :: Linux
Classifier: Operating System :: MacOS :: MacOS X
Classifier: Programming Language :: Python :: 2.7
Classifier: Programming Language :: Python :: 3
Classifier: Topic :: Utilities
